sharded/__init__.py
sharded/__main__.py
sharded/config.py
sharded/main.py
sharded/services.py
sharded/CLI/addons.py
sharded/CLI/main.py
sharded/cogs/moderation.py
shardedbot-0.0.1.dist-info/METADATA
shardedbot-0.0.1.dist-info/WHEEL
shardedbot-0.0.1.dist-info/entry_points.txt
shardedbot-0.0.1.dist-info/licenses/LICENSE
shardedbot-0.0.1.dist-info/RECORD
