Metadata-Version: 2.4
Name: shardedbot
Version: 0.0.1
Summary: Sharded is a python powered discord bot which aims to bring advanced moderation, community management features, and customization to the users.
License-File: LICENSE
Requires-Python: >=3.9
Requires-Dist: appwrite>=9.0.3
Requires-Dist: discord-py[voice]>=2.5.2
Requires-Dist: python-dotenv>=1.0.1
Requires-Dist: requests>=2.32.3
Requires-Dist: rich>=13.9.4
Requires-Dist: typer>=0.15.2
